cbytesparse/c.pxd
cbytesparse/c.c
cbytesparse/__init__.pxd
cbytesparse/__init__.py
cbytesparse/c.cpython-38-darwin.so
cbytesparse/base.py
cbytesparse/py.py
cbytesparse/c.pyx
cbytesparse-0.0.6.dist-info/RECORD
cbytesparse-0.0.6.dist-info/LICENSE
cbytesparse-0.0.6.dist-info/WHEEL
cbytesparse-0.0.6.dist-info/AUTHORS.rst
cbytesparse-0.0.6.dist-info/top_level.txt
cbytesparse-0.0.6.dist-info/METADATA
