Metadata-Version: 2.1
Name: cbytesparse
Version: 0.0.6
Summary: Library to handle sparse bytes within a virtual memory space
Author: Caroline Russell
Author-email: Andrea Zoppi <texzk@email.it>
License: BSD-2-Clause
Project-URL: documentation, https://cbytesparse.readthedocs.io
Project-URL: source, https://github.com/TexZK/cbytesparse
Project-URL: tracker, https://github.com/TexZK/cbytesparse/issues
Classifier: Development Status :: 3 - Alpha
Classifier: Intended Audience :: Developers
Classifier: License :: OSI Approved :: BSD License
Classifier: Operating System :: OS Independent
Classifier: Programming Language :: Cython
Classifier: Programming Language :: Python
Classifier: Programming Language :: Python :: 3
Classifier: Programming Language :: Python :: 3 :: Only
Classifier: Programming Language :: Python :: 3.7
Classifier: Programming Language :: Python :: 3.8
Classifier: Programming Language :: Python :: 3.9
Classifier: Programming Language :: Python :: 3.10
Classifier: Programming Language :: Python :: 3.11
Classifier: Programming Language :: Python :: Implementation :: CPython
Classifier: Topic :: Scientific/Engineering :: Interface Engine/Protocol Translator
Classifier: Topic :: Software Development
Classifier: Topic :: Software Development :: Embedded Systems
Classifier: Topic :: Utilities
Requires-Python: >=3.7
License-File: LICENSE
License-File: AUTHORS.rst
Requires-Dist: bytesparse (>=0.0.6)
Provides-Extra: bdist
Requires-Dist: cbuildwheel ; extra == 'bdist'
Requires-Dist: pytest ; extra == 'bdist'
Provides-Extra: scripts
Requires-Dist: Cython ; extra == 'scripts'
Provides-Extra: testing
Requires-Dist: Cython ; extra == 'testing'
Requires-Dist: pytest ; extra == 'testing'
